.hgignore
.hgtags
CREDITS.txt
HISTORY.txt
LICENSE.txt
MANIFEST.in
bootstrap.py
buildout.cfg
setup.py
src/fcrepo/README.txt
src/fcrepo/__init__.py
src/fcrepo/client.py
src/fcrepo/connection.py
src/fcrepo/datastream.py
src/fcrepo/object.py
src/fcrepo/scripts.py
src/fcrepo/utils.py
src/fcrepo/wadl.py
src/fcrepo.egg-info/PKG-INFO
src/fcrepo.egg-info/SOURCES.txt
src/fcrepo.egg-info/dependency_links.txt
src/fcrepo.egg-info/entry_points.txt
src/fcrepo.egg-info/not-zip-safe
src/fcrepo.egg-info/requires.txt
src/fcrepo.egg-info/top_level.txt
src/fcrepo/tests/__init__.py
src/fcrepo/tests/test_docs.py