Metadata-Version: 1.0
Name: fcrepo
Version: 1.1
Summary: API implementation for the Fedora Commons Repository platform
Home-page: UNKNOWN
Author: Infrae
Author-email: info@infrae.com
License: BSD
Platform: UNKNOWN
Classifier: Development Status :: 4 - Beta
Classifier: Programming Language :: Python
Classifier: License :: OSI Approved :: BSD License
Classifier: Topic :: Software Development :: Libraries :: Python Modules
Classifier: Environment :: Web Environment
Classifier: Intended Audience :: Science/Research
